{
  "en-US": {
    "views": {
      "HomePage": "Home",
      "AboutUs": "About Us",
      "EducationTeaching": "Education",
      "StudentLife": "Student Life",
      "JoinUs": "Join Us",
      "NewsPage": "News"
    },
    "HomePage": {
      "ReadMore": "Read More",
      "SecondSection": {
        "Title": "我们是北京中学国际部",
        "Content": "北京中学位于北京市朝阳区东坝，是北京市发展最快的地区之一，拥有100余所小学、70余所中学和20余所高中。学校被广泛认为是最有声望和发展最快的高中之一。\n\n东坝一带经济基础多元化，被指定为北京第四个使馆区。北京中学强调高标准，并期望学校中的每个人都为一个更美好的世界而努力。"
      },
      "EducationPhilosophy": {
        "Title": "Education Philosophy",
        "1": {
          "Top": "Motto",
          "Bottom": "Better Me, Better World."
        },
        "2": {
          "Top": "Spirit",
          "Bottom": "Embrace the harmony and differences."
        },
        "3": {
          "Top": "Key Competency",
          "Bottom": "Benevolence / Wisdom \nBravery / Happiness"
        },
        "4": {
          "Top": "Cultivation",
          "Bottom": "To Learn / To Cooperate \nTo Live / To Innovate"
        }
      },
      "AdmissionResults": {
        "Title": "Meet BAID",
        "TitleSub": "录取结果",
        "Content": "2017-2022，三届毕业生，从0到1，垂直进步。\n首届学生1名大学被哈佛大学录取、74%学生被美国TOP30大学录取，第二届学生100%被美国前30大学和文理学院录取，第三届学生藤校录取率高达25%。\n录取院校包括哈佛大学、斯坦福大学、宾夕法尼亚大学、约翰斯·霍普金斯大学、加州理工大学、达特茅斯学院、康奈尔大学、范德堡大学、加州大学洛杉矶分校、加州大学伯克利分校、埃默里大学、南加州大学、弗吉尼亚大学、纽约大学、斯沃斯莫学院、波莫纳学院、韦尔斯利学院、卡尔顿学院、史密斯学院、罗德岛设计学院、剑桥大学、伦敦政治经济学院、伦敦大学学院、伦敦国王学院、爱丁堡大学、巴斯大学、布里斯托大学、曼彻斯特大学、华威大学、伦敦艺术大学、多伦多大学、麦吉尔大学、英属哥伦比亚大学、澳大利亚国立大学、墨尔本大学、悉尼大学、庆应大学、早稻田大学、奥克兰大学……"
      },
      "News": {
        "Title": "News"
      }
    },
    "AboutUs": {
      "Title": "About Us",
      "Overview": {
        "Title": "Overview",
        "Content": "English"
      },
      "Alumni": {
        "Title": "Alumni",
        "Content": "在这种困难的抉择下，本人思来想去，寝食难安。 毕业生因何而发生？ 德谟克利特说过一句富有哲理的话，节制使快乐增加并使享受加强。这启发了我， 老子曾经说过，知人者智，自知者明。胜人者有力，自胜者强。这句话语虽然很短，但令我浮想联翩。 我们都知道，只要有意义，那么就必须慎重考虑。 韩非在不经意间这样说过，内外相应，言行相称。我希望诸位也能好好地体会这句话。 叔本华说过一句富有哲理的话，意志是一个强壮的盲人，倚靠在明眼的跛子肩上。这不禁令我深思。 在这种困难的抉择下，本人思来想去，寝食难安。 现在，解决毕业生的问题，是非常非常重要的。"
      },
      "Accreditation": {
        "Title": "Accreditation",
        "Content": "English Content",
        "AP": "AP Authorized",
        "ACT": "ACT GAC Authorized",
        "CIS": "CIS Accredited",
        "Cambridge": "Cambridge International School",
        "Apple": "Apple Distinguished School"
      },
      "Data": {
        "Title": "Data",
        "Ratio": "1:6"
      }
    },
    "EducationTeaching": {
      "Curriculums": {
        "Title": "Curriculums",
        "1": {
          "Title": "基础课程",
          "Description": "基础课程服务于学生全面发展，执行国家课程和地方课程，并有一定的校本化改进，涵盖了所有的必修课程，使学生能够掌握扎实的学科基础，初步具备学科核心素养，切实落实全体学生的全面发展和共同发展。"
        },
        "2": {
          "Title": "潜能课程",
          "Description": "潜能课程服务于学生卓越发展。为了满足学生的优势潜能发展需求，真正实现扬长避短，志趣养成，学校建设了领导力系列，创造力系列，特别才能三大系列的潜能课程。积极开设项目课程，竞赛课程，专项研究，体育特长，艺术设计等课程，为培养学生的潜能和创造能力奠定基础。"
        },
        "3": {
          "Title": "拓展课程",
          "Description": "拓展课程是选修课程，服务于学生多元发展，根据学生的升学方向和多样化发展需求提供。既有选择性必修课程，根据学生兴趣爱好和升学意向设置。学生选择适合的科目进行学习，获得相应学分，达到毕业学分的要求。也有学校统筹规划开设的课程，以本校教师自主开发为主，鼓励学生自主创建社团课程，统筹多方资源主体共同建设的系列选修课程。如STEM课程把科学技术、工程、数学的综合应用，通过基于真实问题解决的探究，促进学生在实践中学习运用知识，发展创新精神和问题解决能力。"
        }
      },
      "LearningMethods": {
        "Title": "Learning Methods",
        "Method1": {
          "Title": "标一\n标一\n标一",
          "BigTitle": "大标题一大标题大标题大标题",
          "Description": "内容内容内容内容内容内容内容内容内容内容内容内容内容内容内容内容内容内容"
        },
        "Method2": {
          "Title": "标二\n标二\n标二",
          "BigTitle": "大标题二大标题大标题大标题",
          "Description": "内容内容内容内容内容内容内容内容内容内容内容内容内容内容内容内容内容内容"
        },
        "Method3": {
          "Title": "标三\n标三\n标三",
          "BigTitle": "大标题三大标题大标题大标题",
          "Description": "内容内容内容内容内容内容内容内容内容内容内容内容内容内容内容内容内容内容"
        },
        "Method4": {
          "Title": "标四\n标四\n标四",
          "BigTitle": "大标题三大标题大标题大标题",
          "Description": "内容内容内容内容内容内容内容内容内容内容内容内容内容内容内容内容内容内容"
        }
      },
      "StudentGuidance": {
        "Title": "Student Guidance",
        "Content": {
          "Title": "标题",
          "Description": "蚊子蚊子蚊子蚊子蚊子蚊子蚊子蚊子蚊子蚊子蚊子蚊子蚊子蚊子"
        }
      },
      "WonderfulMoments": {
        "Title": "Wonderful Moments",
        "Slides": {
          "Slide1": {
            "Title": "标题1",
            "Description": "介绍介绍介绍1"
          },
          "Slide2": {
            "Title": "标题2",
            "Description": "介绍介绍介绍2"
          },
          "Slide3": {
            "Title": "标题3",
            "Description": "介绍介绍介绍3"
          }
        }
      }
    },
    "StudentLife": {
      "Clubs": {
        "Title": "Clubs",
        "Club1": {
          "Name": "法语社",
          "Description": "法语社团成立于2021年，由两位学习多年法语的社长带领。在这里，我们从基础开始，一步一步由字母到单词，从语法到日常对话。当然，比学习法语更重要的，是了解法国文化。欢迎加入法语社团！"
        },
        "Club2": {
          "Name": "SLSD",
          "Description": "我们，SLSD（The Students League of Sustainable Development），致力于提高中学生对可持续发展的关注度与认识，吸引更多的同学参与可持续发展的实践和科学研究活动。通过推广宣传有关可持续发展的国内外动态、举办论坛活动、分析研究、培训信息和竞赛活动等、分享与可持续发展相关的文章，培养中学生的可持续发展观念及在可持续发展领域的研究兴趣和能力。"
        },
        "Club3": {
          "Name": "BA Times",
          "Description": "BA Times，由Livia和Yimo创办的英文创意写作社团。目前以New York Times比赛为框架，带领社员游走在文字、情感、逻辑与想象力共同组成的海洋。开放兼包、表达和松弛是我们的关键词。"
        },
        "Club4": {
          "Name": "小花小草",
          "Description": "小花小草由国际部高瑞韩同学和张礼涵同学发起，秉承爱护植物、科普植物的原则，为北京中学植物挂牌。项目旨在帮助广大学生群体和老师群体更深一步了解校园植物，欣赏大自然的美丽与和谐。 本项目另有制作中的植物纪念册，保存北中人的珍贵记忆。"
        },
        "Club5": {
          "Name": "神经科学社",
          "Description": "北京中学神经科学社是由国际部高瑞韩同学创办的学生自主社团，秉承着互帮互助、深入探索的原则，为对生物/心理学感兴趣的同学们培养神经科学领域的入门知识。社团主要以社长/学生授课、实验室解剖、案例学习以及视频诊断等形式活动，保证每个社员的高参与度以及思维训练。"
        },
        "Club6": {
          "Name": "绿眼碳排放",
          "Description": "我们是一个由北京中学学生组成的自主项目。我们的目标是加强人们对全球变暖的危急意识，动员大家进行低碳生活。目前我们做的工作有两部分：1. 搭建一个关于中国各碳排放的信息中心，提供数据的可视化、最新科研文献、以及其他相关的相关活动。这是我们的建设的网站（https://www.green-spectator.com/）上，我们希望通过数据的公开化来加强对政府工作的监督，并提升人们对于中国温室气体排放的重视。2. 在校园开展废纸回收活动等，培养同学们的环保节约意识。"
        }
      },
      "Activities": {
        "Title": "Activities",
        "Event1": {
          "Name": "英文戏剧节",
          "Description": "英文戏剧节介绍"
        },
        "Event2": {
          "Name": "露营",
          "Description": "露营介绍"
        },
        "Event3": {
          "Name": "“北中杯”",
          "Description": "“北中杯”介绍"
        },
        "Event4": {
          "Name": "自我挑战营",
          "Description": "自我挑战营介绍"
        },
        "Event5": {
          "Name": "国际风情周",
          "Description": "国际风情周介绍"
        },
        "Event6": {
          "Name": "北中好声音",
          "Description": "北中好声音介绍"
        }
      }
    }
  },
  "zh-CN": {
    "views": {
      "HomePage": "首页",
      "AboutUs": "关于我们",
      "EducationTeaching": "教育教学",
      "StudentLife": "学生生活",
      "JoinUs": "加入我们",
      "NewsPage": "新闻"
    },
    "HomePage": {
      "ReadMore": "了解更多",
      "SecondSection": {
        "Title": "我们是北京中学国际部",
        "Content": "北京中学位于北京市朝阳区东坝，是北京市发展最快的地区之一，拥有100余所小学、70余所中学和20余所高中。学校被广泛认为是最有声望和发展最快的高中之一。\n\n东坝一带经济基础多元化，被指定为北京第四个使馆区。北京中学强调高标准，并期望学校中的每个人都为一个更美好的世界而努力。"
      },
      "EducationPhilosophy": {
        "Title": "办学理念",
        "1": {
          "Top": "校训",
          "Bottom": "世界因我更美好"
        },
        "2": {
          "Top": "校风",
          "Bottom": "和而不同 / \n乐在其中"
        },
        "3": {
          "Top": "核心素养",
          "Bottom": "仁 / 智 / 勇 / 乐"
        },
        "4": {
          "Top": "培养路径",
          "Bottom": "学会学习 / 学会共处 / \n学会生活 / 学会创新"
        }
      },
      "AdmissionResults": {
        "Title": "遇见BAID",
        "TitleSub": "录取结果",
        "Content": "2017-2022，三届毕业生，从0到1，垂直进步。\n首届学生1名大学被哈佛大学录取、74%学生被美国TOP30大学录取，第二届学生100%被美国前30大学和文理学院录取，第三届学生藤校录取率高达25%。\n录取院校包括哈佛大学、斯坦福大学、宾夕法尼亚大学、约翰斯·霍普金斯大学、加州理工大学、达特茅斯学院、康奈尔大学、范德堡大学、加州大学洛杉矶分校、加州大学伯克利分校、埃默里大学、南加州大学、弗吉尼亚大学、纽约大学、斯沃斯莫学院、波莫纳学院、韦尔斯利学院、卡尔顿学院、史密斯学院、罗德岛设计学院、剑桥大学、伦敦政治经济学院、伦敦大学学院、伦敦国王学院、爱丁堡大学、巴斯大学、布里斯托大学、曼彻斯特大学、华威大学、伦敦艺术大学、多伦多大学、麦吉尔大学、英属哥伦比亚大学、澳大利亚国立大学、墨尔本大学、悉尼大学、庆应大学、早稻田大学、奥克兰大学……"
      },
      "News": {
        "Title": "新闻"
      }
    },
    "AboutUs": {
      "Overview": {
        "Title": "学校概况",
        "Content": "北京中学成立于2013年9月，是经北京市政府批准，由朝阳区政府创办的一所十二年一贯制的公办学校，致力于办成一所具有北京风格、中国气质与世界胸怀的现代学校。\n\n学校坚持立德树人，坚持社会主义核心价值观，坚持依法治校与改革创新，致力于培育学校文化的种子。确立“世界因我更美好”的校训，崇尚“和而不同、乐在其中”的校风，以“享幸福人生，做中华栋梁”为培养目标，以“仁、智、勇、乐”为学生成长的核心素养，引导学生学会学习、学会共处、学会生活、学会创新，促进学生全面而自由的成长，积极构建符合时代要求与学生成长规律的新型育人模式，培养学生成长为具有健康品格、爱国情怀和创新精神的优秀人才。\n\n2017年，北京中学开始国际方向的办学探索，2020年获北京市教委批准高中中外合作办学项目，采用中国高中课程、AP课程与特色课程相融合的课程体系。学校是AP授权校，CIS认证成员学校，ACT GAC授权学校。\n\n北京中学在教育教学改革创新的道路上坚定前行，2013年以来连续八年举办“构建未来理想学校”学术研讨会，在朝阳区乃至北京市基础教育领域形成了较好的影响力。"
      },
      "Alumni": {
        "Title": "毕业生介绍",
        "Content": "在这种困难的抉择下，本人思来想去，寝食难安。 毕业生因何而发生？ 德谟克利特说过一句富有哲理的话，节制使快乐增加并使享受加强。这启发了我， 老子曾经说过，知人者智，自知者明。胜人者有力，自胜者强。这句话语虽然很短，但令我浮想联翩。 我们都知道，只要有意义，那么就必须慎重考虑。 韩非在不经意间这样说过，内外相应，言行相称。我希望诸位也能好好地体会这句话。 叔本华说过一句富有哲理的话，意志是一个强壮的盲人，倚靠在明眼的跛子肩上。这不禁令我深思。 在这种困难的抉择下，本人思来想去，寝食难安。 现在，解决毕业生的问题，是非常非常重要的。",
        "1": {
          "Name": "田学姐",
          "Quote": "这里是起点，是舞台，是被给予信任的空间。我在这里学着成为一个全面发展的人，探索自我，理解他人，心怀社会。这里成就了中学阶段的我，相信也会成就每一位北中人。"
        },
        "2": {
          "Name": "王学长",
          "Quote": "我十分感谢北中对于学生个性化发展的支持和包容。在北京中学的这几年，我获得了兼收并蓄的思考方式，学会了如何培养以热情为导向的自主能动性。同时，也发展了可以伴随我一生的兴趣和友谊。"
        },
        "3": {
          "Name": "杨学姐",
          "Quote": "在我心中北中的七年像一场温柔缱绻的梦。我在这里成长，蜕变，变成了我喜欢的模样。我永远珍视这里的每一段回忆，每每回首时，它们都能成为我继续前行的力量。"
        }
      },
      "Accreditation": {
        "Title": "认证",
        "Content": "北京中学国际部获得美国College Board认证成为AP课程学校；是中国第一家获得CIS认证校资格的公立中学；授权为全球ACT-GAC官方教学及考试中心；是剑桥课程授权学校；被苹果授予“苹果杰出学校”称号。",
        "AP": "AP 授权校",
        "ACT": "ACT GAC 授权校",
        "CIS": "CIS 认证校",
        "Cambridge": "剑桥国际学校",
        "Apple": "Apple 杰出学校"
      },
      "Data": {
        "Title": "数据一览",
        "Ratio": "1:6"
      }
    },
    "JoinUs": {
      "Join": "加入就现在",
      "Student": {
        "Title": "北京中学国际部招生要求",
        "Content": "2013年，经北京市政府批准、由朝阳区政府主办的北京中学正式建校，备受社会各界关注。九年来，在市区教委的关心支持下，教师们静心推行教育改革创新，以爱和温暖守护同学们的全面成长，以专业引领同学们的发展。2017年，为了满足部分学生和家长的多元化升学需求，搭建成长的立交桥，北京中学组建国际方向班级。北京中学非常重视培养学生的个性化发展，学校全力为学生提供学术、科研、表达、服务、艺术、运动等领域的多元化平台和支持，小而精的班级规模让每个孩子的潜能被激发，每个孩子的成长都得到量身定制的呵护，逐步成长为国家和世界所需要的适应时代发展和变革的创新人才。\n学校坚持中国立场、开放多元、融合创新，基于课程改革特色实践，和美国格伦罗克高中共同开发了国际教育体系课程，包括高中基础课程、AP课程、特色选修课程，满足学生个性化发展需求。\n北京中学国际部招生，通过中考统招。2023年国际部计划招生100人，为AP课程合作办学项目。但是本着为每一位孩子尽可能提供足够的资源支持的原则，23年会根据报考学生情况进行加试考核，择优录取。（人数是根据往年定的，23年待定）",
        "Join": "学生申请入口"
      },
      "Faculty": {
        "Title": "北京中学国际部招聘教师要求",
        "Content": "在这种困难的抉择下，本人思来想去，寝食难安。 毕业生因何而发生？ 德谟克利特说过一句富有哲理的话，节制使快乐增加并使享受加强。这启发了我， 老子曾经说过，知人者智，自知者明。胜人者有力，自胜者强。这句话语虽然很短，但令我浮想联翩。 我们都知道，只要有意义，那么就必须慎重考虑。 韩非在不经意间这样说过，内外相应，言行相称。我希望诸位也能好好地体会这句话。 叔本华说过一句富有哲理的话，意志是一个强壮的盲人，倚靠在明眼的跛子肩上。这不禁令我深思。 在这种困难的抉择下，本人思来想去，寝食难安。 现在，解决毕业生的问题，是非常非常重要的。",
        "Join": "教师申请入口"
      }
    },
    "EducationTeaching": {
      "Curriculums": {
        "Title": "课程体系",
        "1": {
          "Title": "基础课程",
          "Description": "基础课程服务于学生全面发展，执行国家课程和地方课程，并有一定的校本化改进，涵盖了所有的必修课程，使学生能够掌握扎实的学科基础，初步具备学科核心素养，切实落实全体学生的全面发展和共同发展。"
        },
        "2": {
          "Title": "潜能课程",
          "Description": "潜能课程服务于学生卓越发展。为了满足学生的优势潜能发展需求，真正实现扬长避短，志趣养成，学校建设了领导力系列，创造力系列，特别才能三大系列的潜能课程。积极开设项目课程，竞赛课程，专项研究，体育特长，艺术设计等课程，为培养学生的潜能和创造能力奠定基础。"
        },
        "3": {
          "Title": "拓展课程",
          "Description": "拓展课程是选修课程，服务于学生多元发展，根据学生的升学方向和多样化发展需求提供。既有选择性必修课程，根据学生兴趣爱好和升学意向设置。学生选择适合的科目进行学习，获得相应学分，达到毕业学分的要求。也有学校统筹规划开设的课程，以本校教师自主开发为主，鼓励学生自主创建社团课程，统筹多方资源主体共同建设的系列选修课程。如STEM课程把科学技术、工程、数学的综合应用，通过基于真实问题解决的探究，促进学生在实践中学习运用知识，发展创新精神和问题解决能力。"
        }
      },
      "LearningMethods": {
        "Title": "学习方式",
        "Method1": {
          "Title": "标一\n标一\n标一",
          "BigTitle": "大标题一大标题大标题大标题",
          "Description": "内容内容内容内容内容内容内容内容内容内容内容内容内容内容内容内容内容内容"
        },
        "Method2": {
          "Title": "标二\n标二\n标二",
          "BigTitle": "大标题二大标题大标题大标题",
          "Description": "内容内容内容内容内容内容内容内容内容内容内容内容内容内容内容内容内容内容"
        },
        "Method3": {
          "Title": "标三\n标三\n标三",
          "BigTitle": "大标题三大标题大标题大标题",
          "Description": "内容内容内容内容内容内容内容内容内容内容内容内容内容内容内容内容内容内容"
        },
        "Method4": {
          "Title": "标四\n标四\n标四",
          "BigTitle": "大标题三大标题大标题大标题",
          "Description": "内容内容内容内容内容内容内容内容内容内容内容内容内容内容内容内容内容内容"
        }
      },
      "StudentGuidance": {
        "Title": "学生指导",
        "Content": {
          "Title": "标题",
          "Description": "蚊子蚊子蚊子蚊子蚊子蚊子蚊子蚊子蚊子蚊子蚊子蚊子蚊子蚊子"
        }
      },
      "WonderfulMoments": {
        "Title": "精彩瞬间",
        "Slides": {
          "Slide1": {
            "Title": "标题1",
            "Description": "介绍介绍介绍1"
          },
          "Slide2": {
            "Title": "标题2",
            "Description": "介绍介绍介绍2"
          },
          "Slide3": {
            "Title": "标题3",
            "Description": "介绍介绍介绍3"
          }
        }
      }
    },
    "StudentLife": {
      "Clubs": {
        "Title": "学生社团",
        "Club1": {
          "Name": "法语社",
          "Description": "法语社团成立于2021年，由两位学习多年法语的社长带领。在这里，我们从基础开始，一步一步由字母到单词，从语法到日常对话。当然，比学习法语更重要的，是了解法国文化。欢迎加入法语社团！"
        },
        "Club2": {
          "Name": "SLSD",
          "Description": "我们，SLSD（The Students League of Sustainable Development），致力于提高中学生对可持续发展的关注度与认识，吸引更多的同学参与可持续发展的实践和科学研究活动。通过推广宣传有关可持续发展的国内外动态、举办论坛活动、分析研究、培训信息和竞赛活动等、分享与可持续发展相关的文章，培养中学生的可持续发展观念及在可持续发展领域的研究兴趣和能力。"
        },
        "Club3": {
          "Name": "BA Times",
          "Description": "BA Times，由Livia和Yimo创办的英文创意写作社团。目前以New York Times比赛为框架，带领社员游走在文字、情感、逻辑与想象力共同组成的海洋。开放兼包、表达和松弛是我们的关键词。"
        },
        "Club4": {
          "Name": "小花小草",
          "Description": "小花小草由国际部高瑞韩同学和张礼涵同学发起，秉承爱护植物、科普植物的原则，为北京中学植物挂牌。项目旨在帮助广大学生群体和老师群体更深一步了解校园植物，欣赏大自然的美丽与和谐。 本项目另有制作中的植物纪念册，保存北中人的珍贵记忆。"
        },
        "Club5": {
          "Name": "神经科学社",
          "Description": "北京中学神经科学社是由国际部高瑞韩同学创办的学生自主社团，秉承着互帮互助、深入探索的原则，为对生物/心理学感兴趣的同学们培养神经科学领域的入门知识。社团主要以社长/学生授课、实验室解剖、案例学习以及视频诊断等形式活动，保证每个社员的高参与度以及思维训练。"
        },
        "Club6": {
          "Name": "绿眼碳排放",
          "Description": "我们是一个由北京中学学生组成的自主项目。我们的目标是加强人们对全球变暖的危急意识，动员大家进行低碳生活。目前我们做的工作有两部分：1. 搭建一个关于中国各碳排放的信息中心，提供数据的可视化、最新科研文献、以及其他相关的相关活动。这是我们的建设的网站（https://www.green-spectator.com/）上，我们希望通过数据的公开化来加强对政府工作的监督，并提升人们对于中国温室气体排放的重视。2. 在校园开展废纸回收活动等，培养同学们的环保节约意识。"
        }
      },
      "Activities": {
        "Title": "活动",
        "Event1": {
          "Name": "英文戏剧节",
          "Description": "英文戏剧节介绍"
        },
        "Event2": {
          "Name": "露营",
          "Description": "露营介绍"
        },
        "Event3": {
          "Name": "“北中杯”",
          "Description": "“北中杯”介绍"
        },
        "Event4": {
          "Name": "自我挑战营",
          "Description": "自我挑战营介绍"
        },
        "Event5": {
          "Name": "国际风情周",
          "Description": "国际风情周介绍"
        },
        "Event6": {
          "Name": "北中好声音",
          "Description": "北中好声音介绍"
        }
      }
    }
  }
}